{"api":{"services":["StatsService"],"tag":"api"},"inbounds":[{"listen":"127.0.0.1","port":10808,"protocol":"socks","settings":{"allowTransparent":false,"auth":"noauth","udp":true},"sniffing":{"destOverride":["http","tls"],"enabled":true},"tag":"socks"},{"listen":"127.0.0.1","port":10809,"protocol":"http","settings":{"allowTransparent":false,"auth":"noauth","udp":true},"sniffing":{"destOverride":["http","tls"],"enabled":true},"tag":"http"},{"listen":"0.0.0.0","port":10810,"protocol":"socks","settings":{"allowTransparent":false,"auth":"noauth","udp":true},"sniffing":{"destOverride":["http","tls"],"enabled":true},"tag":"socks2"},{"listen":"0.0.0.0","port":10811,"protocol":"http","settings":{"allowTransparent":false,"auth":"noauth","udp":true},"sniffing":{"destOverride":["http","tls"],"enabled":true},"tag":"http2"},{"listen":"127.0.0.1","port":4064,"protocol":"dokodemo-door","settings":{"address":"127.0.0.1","allowTransparent":false,"udp":false},"tag":"api"}],"log":{"access":"","error":"","loglevel":"warning"},"observatory":{"probeInterval":"20s","subjectSelector":["proxy0","proxy1","proxy2","proxy3","proxy4","proxy5","proxy6","proxy7","proxy8","proxy9","proxy10","proxy11","proxy12","proxy13","proxy14","proxy15","proxy16","proxy17","proxy18","proxy19","proxy20","proxy21","proxy22","proxy23","proxy24","proxy25","proxy26","proxy27","proxy28","proxy29","proxy30","proxy31","proxy32","proxy33","proxy34","proxy35","proxy36","proxy37","proxy38","proxy39","proxy40","proxy41","proxy42","proxy43","proxy44","proxy45","proxy46","proxy47","proxy48","proxy49","proxy50","proxy51","proxy52","proxy53","proxy54","proxy55","proxy56","proxy57","proxy58","proxy59","proxy60","proxy61","proxy62","proxy63","proxy64","proxy65","proxy66","proxy67","proxy68","proxy69","proxy70"]},"outbounds":[{"mux":{"enabled":false,"concurrency":-1},"protocol":"vmess","settings":{"vnext":[{"address":"ca1.sharecentre.online","port":443,"users":[{"id":"20e92881-5fb4-4b05-bc77-57929476dc69","alterId":0,"email":"t@t.tt","security":"auto"}]}]},"streamSettings":{"network":"ws","security":"tls","tlsSettings":{"allowInsecure":true,"serverName":"ca1.sharecentre.online"},"wsSettings":{"path":"/shirker","headers":{"Host":"ca1.sharecentre.online"}}},"tag":"proxy0"},{"mux":{"enabled":false,"concurrency":-1},"protocol":"vmess","settings":{"vnext":[{"address":"203.30.191.20","port":443,"users":[{"id":"5f64fa65-7b14-49c5-954d-aa15c6bfcacd","alterId":0,"email":"t@t.tt","security":"auto"}]}]},"streamSettings":{"network":"ws","security":"tls","tlsSettings":{"allowInsecure":true,"serverName":"clash6.ssr-free.xyz"},"wsSettings":{"path":"/dongtaiwang.com","headers":{"Host":"clash6.ssr-free.xyz"}}},"tag":"proxy1"},{"mux":{"enabled":false,"concurrency":-1},"protocol":"vmess","settings":{"vnext":[{"address":"cf-lt.sharecentre.online","port":443,"users":[{"id":"20e92881-5fb4-4b05-bc77-57929476dc69","alterId":0,"email":"t@t.tt","security":"aes-128-gcm"}]}]},"streamSettings":{"network":"ws","security":"tls","tlsSettings":{"allowInsecure":true,"serverName":"ca1.sharecentre.online"},"wsSettings":{"path":"/shirker","headers":{"Host":"ca1.sharecentre.online"}}},"tag":"proxy2"},{"mux":{"enabled":false,"concurrency":-1},"protocol":"vmess","settings":{"vnext":[{"address":"zfc.windowsupdate1.com","port":443,"users":[{"id":"769c2da7-add3-42e8-a03c-07be9fcf483c","alterId":0,"email":"t@t.tt","security":"auto"}]}]},"streamSettings":{"network":"ws","security":"tls","tlsSettings":{"allowInsecure":true,"serverName":"nl2.yfjc.sbs"},"wsSettings":{"path":"/yfjc/nl2?ed=2048","headers":{"Host":"nl2.yfjc.sbs"}}},"tag":"proxy3"},{"mux":{"enabled":false,"concurrency":-1},"protocol":"vmess","settings":{"vnext":[{"address":"zfc.windowsupdate1.com","port":443,"users":[{"id":"769c2da7-add3-42e8-a03c-07be9fcf483c","alterId":0,"email":"t@t.tt","security":"auto"}]}]},"streamSettings":{"network":"ws","security":"tls","tlsSettings":{"allowInsecure":true,"serverName":"us3.yfjc.sbs"},"wsSettings":{"path":"/yfjc/us3?ed=2048","headers":{"Host":"us3.yfjc.sbs"}}},"tag":"proxy4"},{"mux":{"enabled":false,"concurrency":-1},"protocol":"vless","settings":{"vnext":[{"address":"v2ray5.v2rayfree2.xyz","port":443,"users":[{"id":"3dbf8df2-452d-49af-92de-a1789775de9f","alterId":0,"email":"t@t.tt","security":"none","encryption":"none","flow":""}]}]},"streamSettings":{"network":"ws","security":"tls","tlsSettings":{"allowInsecure":true,"serverName":""},"wsSettings":{"path":"/ray","headers":{"Host":""}}},"tag":"proxy5"},{"mux":{"enabled":false,"concurrency":-1},"protocol":"vmess","settings":{"vnext":[{"address":"ca1.sharecentre.online","port":443,"users":[{"id":"20e92881-5fb4-4b05-bc77-57929476dc69","alterId":0,"email":"t@t.tt","security":"none"}]}]},"streamSettings":{"network":"ws","security":"tls","tlsSettings":{"allowInsecure":true,"serverName":"ca1.sharecentre.online"},"wsSettings":{"path":"/shirker","headers":{"Host":"ca1.sharecentre.online"}}},"tag":"proxy6"},{"mux":{"enabled":false,"concurrency":-1},"protocol":"vmess","settings":{"vnext":[{"address":"zfc.windowsupdate1.com","port":443,"users":[{"id":"769c2da7-add3-42e8-a03c-07be9fcf483c","alterId":0,"email":"t@t.tt","security":"auto"}]}]},"streamSettings":{"network":"ws","security":"tls","tlsSettings":{"allowInsecure":true,"serverName":"us1.yfjc.sbs"},"wsSettings":{"path":"/yfjc/us1?ed=2048","headers":{"Host":"us1.yfjc.sbs"}}},"tag":"proxy7"},{"mux":{"enabled":false,"concurrency":-1},"protocol":"vmess","settings":{"vnext":[{"address":"23.227.38.20","port":443,"users":[{"id":"c5a2d7b8-bf84-4f97-8577-b9b87f2baaf7","alterId":0,"email":"t@t.tt","security":"auto"}]}]},"streamSettings":{"network":"ws","security":"tls","tlsSettings":{"allowInsecure":true,"serverName":"oplg1.cfcdn2.xyz"},"wsSettings":{"path":"/AUIKN8AU","headers":{"Host":"oplg1.cfcdn2.xyz"}}},"tag":"proxy8"},{"mux":{"enabled":false,"concurrency":-1},"protocol":"vmess","settings":{"vnext":[{"address":"172.67.45.144","port":443,"users":[{"id":"c5a2d7b8-bf84-4f97-8577-b9b87f2baaf7","alterId":0,"email":"t@t.tt","security":"auto"}]}]},"streamSettings":{"network":"ws","security":"tls","tlsSettings":{"allowInsecure":true,"serverName":"oplg1.cfcdn2.xyz"},"wsSettings":{"path":"/AUIKN8AU","headers":{"Host":"oplg1.cfcdn2.xyz"}}},"tag":"proxy9"},{"mux":{"enabled":false,"concurrency":-1},"protocol":"vmess","settings":{"vnext":[{"address":"141.193.213.20","port":443,"users":[{"id":"2b214122-1906-428a-bbb7-a039cbb7cd5c","alterId":0,"email":"t@t.tt","security":"auto"}]}]},"streamSettings":{"network":"ws","security":"tls","tlsSettings":{"allowInsecure":true,"serverName":"fr1.trump2023.org"},"wsSettings":{"path":"/9JZFDTKE","headers":{"Host":"fr1.trump2023.org"}}},"tag":"proxy10"},{"mux":{"enabled":false,"concurrency":-1},"protocol":"vmess","settings":{"vnext":[{"address":"cf-lt.sharecentre.online","port":443,"users":[{"id":"20e92881-5fb4-4b05-bc77-57929476dc69","alterId":0,"email":"t@t.tt","security":"auto"}]}]},"streamSettings":{"network":"ws","security":"tls","tlsSettings":{"allowInsecure":true,"serverName":"ca1.sharecentre.online"},"wsSettings":{"path":"/shirker","headers":{"Host":"ca1.sharecentre.online"}}},"tag":"proxy11"},{"mux":{"enabled":false,"concurrency":-1},"protocol":"vmess","settings":{"vnext":[{"address":"zfc.windowsupdate1.com","port":443,"users":[{"id":"27509613-bbd5-403a-868c-8022d36aa565","alterId":0,"email":"t@t.tt","security":"auto"}]}]},"streamSettings":{"network":"ws","security":"tls","tlsSettings":{"allowInsecure":true,"serverName":"fr1.pqjc.buzz"},"wsSettings":{"path":"/pq/fr1?ed=2048","headers":{"Host":"fr1.pqjc.buzz"}}},"tag":"proxy12"},{"mux":{"enabled":false,"concurrency":-1},"protocol":"vmess","settings":{"vnext":[{"address":"141.193.213.21","port":443,"users":[{"id":"2b214122-1906-428a-bbb7-a039cbb7cd5c","alterId":0,"email":"t@t.tt","security":"auto"}]}]},"streamSettings":{"network":"ws","security":"tls","tlsSettings":{"allowInsecure":true,"serverName":"fr1.trump2023.org"},"wsSettings":{"path":"/9JZFDTKE","headers":{"Host":"fr1.trump2023.org"}}},"tag":"proxy13"},{"mux":{"enabled":false,"concurrency":-1},"protocol":"vmess","settings":{"vnext":[{"address":"zfc.windowsupdate1.com","port":443,"users":[{"id":"769c2da7-add3-42e8-a03c-07be9fcf483c","alterId":0,"email":"t@t.tt","security":"auto"}]}]},"streamSettings":{"network":"ws","security":"tls","tlsSettings":{"allowInsecure":true,"serverName":"nl.yfjc.sbs"},"wsSettings":{"path":"/yfjc/nl?ed=2048","headers":{"Host":"nl.yfjc.sbs"}}},"tag":"proxy14"},{"mux":{"enabled":false,"concurrency":-1},"protocol":"vless","settings":{"vnext":[{"address":"iiir.ddns.net","port":8443,"users":[{"id":"6912aa57-adad-4217-baac-a79391e1e88d","alterId":0,"email":"t@t.tt","security":"none","encryption":"none","flow":""}]}]},"streamSettings":{"network":"ws","security":"tls","tlsSettings":{"allowInsecure":true,"serverName":"wl.setam.fun"},"wsSettings":{"path":"/","headers":{"Host":"wl.setam.fun"}}},"tag":"proxy15"},{"mux":{"enabled":false,"concurrency":-1},"protocol":"vmess","settings":{"vnext":[{"address":"203.30.191.191","port":443,"users":[{"id":"40d496a6-ceeb-4096-baeb-4cc52b205621","alterId":0,"email":"t@t.tt","security":"auto"}]}]},"streamSettings":{"network":"ws","security":"tls","tlsSettings":{"allowInsecure":true,"serverName":"lg1.trump2023.us"},"wsSettings":{"path":"/ECTCJ0DF","headers":{"Host":"lg1.trump2023.us"}}},"tag":"proxy16"},{"mux":{"enabled":false,"concurrency":-1},"protocol":"vmess","settings":{"vnext":[{"address":"zfc.windowsupdate1.com","port":443,"users":[{"id":"769c2da7-add3-42e8-a03c-07be9fcf483c","alterId":0,"email":"t@t.tt","security":"auto"}]}]},"streamSettings":{"network":"ws","security":"tls","tlsSettings":{"allowInsecure":true,"serverName":"us2.yfjc.sbs"},"wsSettings":{"path":"/yfjc/us2?ed=2048","headers":{"Host":"us2.yfjc.sbs"}}},"tag":"proxy17"},{"mux":{"enabled":false,"concurrency":-1},"protocol":"vmess","settings":{"vnext":[{"address":"zfc.windowsupdate1.com","port":443,"users":[{"id":"769c2da7-add3-42e8-a03c-07be9fcf483c","alterId":0,"email":"t@t.tt","security":"auto"}]}]},"streamSettings":{"network":"ws","security":"tls","tlsSettings":{"allowInsecure":true,"serverName":"us2.yfjc.sbs"},"wsSettings":{"path":"/yfjc/us2?ed=2048","headers":{"Host":"us2.yfjc.sbs"}}},"tag":"proxy18"},{"mux":{"enabled":false,"concurrency":-1},"protocol":"vmess","settings":{"vnext":[{"address":"zfc.windowsupdate1.com","port":443,"users":[{"id":"27509613-bbd5-403a-868c-8022d36aa565","alterId":0,"email":"t@t.tt","security":"auto"}]}]},"streamSettings":{"network":"ws","security":"tls","tlsSettings":{"allowInsecure":true,"serverName":"fr1.pqjc.buzz"},"wsSettings":{"path":"/pq/fr1?ed=2048","headers":{"Host":"fr1.pqjc.buzz"}}},"tag":"proxy19"},{"mux":{"enabled":false,"concurrency":-1},"protocol":"vmess","settings":{"vnext":[{"address":"cf-lt.sharecentre.online","port":443,"users":[{"id":"20e92881-5fb4-4b05-bc77-57929476dc69","alterId":0,"email":"t@t.tt","security":"aes-128-gcm"}]}]},"streamSettings":{"network":"ws","security":"tls","tlsSettings":{"allowInsecure":true,"serverName":"hk-2.sharecentre.online"},"wsSettings":{"path":"/shirker","headers":{"Host":"hk-2.sharecentre.online"}}},"tag":"proxy20"},{"mux":{"enabled":false,"concurrency":-1},"protocol":"vmess","settings":{"vnext":[{"address":"zfc.windowsupdate1.com","port":443,"users":[{"id":"769c2da7-add3-42e8-a03c-07be9fcf483c","alterId":0,"email":"t@t.tt","security":"auto"}]}]},"streamSettings":{"network":"ws","security":"tls","tlsSettings":{"allowInsecure":true,"serverName":"us3.yfjc.sbs"},"wsSettings":{"path":"/yfjc/us3?ed=2048","headers":{"Host":"us3.yfjc.sbs"}}},"tag":"proxy21"},{"mux":{"enabled":false,"concurrency":-1},"protocol":"vmess","settings":{"vnext":[{"address":"zfc.windowsupdate1.com","port":443,"users":[{"id":"769c2da7-add3-42e8-a03c-07be9fcf483c","alterId":0,"email":"t@t.tt","security":"auto"}]}]},"streamSettings":{"network":"ws","security":"tls","tlsSettings":{"allowInsecure":true,"serverName":"nl.yfjc.sbs"},"wsSettings":{"path":"/yfjc/nl?ed=2048","headers":{"Host":"nl.yfjc.sbs"}}},"tag":"proxy22"},{"mux":{"enabled":false,"concurrency":-1},"protocol":"vmess","settings":{"vnext":[{"address":"cf-lt.sharecentre.online","port":443,"users":[{"id":"20e92881-5fb4-4b05-bc77-57929476dc69","alterId":0,"email":"t@t.tt","security":"aes-128-gcm"}]}]},"streamSettings":{"network":"ws","security":"tls","tlsSettings":{"allowInsecure":true,"serverName":"ca1.sharecentre.online"},"wsSettings":{"path":"/shirker","headers":{"Host":"ca1.sharecentre.online"}}},"tag":"proxy23"},{"mux":{"enabled":false,"concurrency":-1},"protocol":"vmess","settings":{"vnext":[{"address":"zfc.windowsupdate1.com","port":443,"users":[{"id":"769c2da7-add3-42e8-a03c-07be9fcf483c","alterId":0,"email":"t@t.tt","security":"auto"}]}]},"streamSettings":{"network":"ws","security":"tls","tlsSettings":{"allowInsecure":true,"serverName":"us1.yfjc.sbs"},"wsSettings":{"path":"/yfjc/us1?ed=2048","headers":{"Host":"us1.yfjc.sbs"}}},"tag":"proxy24"},{"mux":{"enabled":false,"concurrency":-1},"protocol":"vmess","settings":{"vnext":[{"address":"tls.admin.tlz.lol","port":8848,"users":[{"id":"53816397-f39d-4d64-cf0d-9f7e3a852184","alterId":0,"email":"t@t.tt","security":"auto"}]}]},"streamSettings":{"network":"ws","security":"tls","tlsSettings":{"allowInsecure":true,"serverName":"tls.admin.tlz.lol"},"wsSettings":{"path":"/","headers":{"Host":"tls.admin.tlz.lol"}}},"tag":"proxy25"},{"mux":{"enabled":false,"concurrency":-1},"protocol":"vmess","settings":{"vnext":[{"address":"cft.hicoom.com","port":443,"users":[{"id":"654f997b-5bea-4c82-9538-35ee57b6fd72","alterId":0,"email":"t@t.tt","security":"auto"}]}]},"streamSettings":{"network":"ws","security":"tls","tlsSettings":{"allowInsecure":true,"serverName":"cft.hicoom.com"},"wsSettings":{"path":"/654f997b-5bea-4c82-9538-35ee57b6fd72","headers":{"Host":"cft.hicoom.com"}}},"tag":"proxy26"},{"mux":{"enabled":false,"concurrency":-1},"protocol":"vmess","settings":{"vnext":[{"address":"ingress-i2.iivvppnn.info","port":38102,"users":[{"id":"79386685-16da-327c-9e14-aa6d702d86bc","alterId":1,"email":"t@t.tt","security":"auto"}]}]},"streamSettings":{"network":"ws","security":"","tlsSettings":{"allowInsecure":true,"serverName":""},"wsSettings":{"path":"/hls/cctv5phd.m3u8","headers":{"Host":""}}},"tag":"proxy27"},{"mux":{"enabled":false,"concurrency":-1},"protocol":"vmess","settings":{"vnext":[{"address":"cs1.bbcloud.life","port":17127,"users":[{"id":"b25693cd-1173-42f3-e609-51062d1c65c5","alterId":0,"email":"t@t.tt","security":"auto"}]}]},"streamSettings":{"network":"ws","security":"","tlsSettings":{"allowInsecure":true,"serverName":"cs1.bbcloud.life"},"wsSettings":{"path":"/@abcdefghijk147","headers":{"Host":"cs1.bbcloud.life"}}},"tag":"proxy28"},{"mux":{"enabled":false,"concurrency":-1},"protocol":"vmess","settings":{"vnext":[{"address":"hla1.6bbt.tk","port":443,"users":[{"id":"6e41c22a-2794-4504-a05a-4f8def6d0bf5","alterId":0,"email":"t@t.tt","security":"auto"}]}]},"streamSettings":{"network":"ws","security":"","tlsSettings":{"allowInsecure":true,"serverName":"6bbt.tk"},"wsSettings":{"path":"/6bbt.tk","headers":{"Host":"6bbt.tk"}}},"tag":"proxy29"},{"mux":{"enabled":false,"concurrency":-1},"protocol":"vmess","settings":{"vnext":[{"address":"zfc.windowsupdate1.com","port":443,"users":[{"id":"769c2da7-add3-42e8-a03c-07be9fcf483c","alterId":0,"email":"t@t.tt","security":"auto"}]}]},"streamSettings":{"network":"ws","security":"tls","tlsSettings":{"allowInsecure":true,"serverName":"nl2.yfjc.sbs"},"wsSettings":{"path":"/yfjc/nl2?ed=2048","headers":{"Host":"nl2.yfjc.sbs"}}},"tag":"proxy30"},{"mux":{"enabled":false,"concurrency":-1},"protocol":"vmess","settings":{"vnext":[{"address":"adlya1.6bbt.tk","port":443,"users":[{"id":"6e41c22a-2794-4504-a05a-4f8def6d0bf5","alterId":0,"email":"t@t.tt","security":"auto"}]}]},"streamSettings":{"network":"ws","security":"","tlsSettings":{"allowInsecure":true,"serverName":"6bbt.tk"},"wsSettings":{"path":"/6bbt.tk","headers":{"Host":"6bbt.tk"}}},"tag":"proxy31"},{"mux":{"enabled":false,"concurrency":-1},"protocol":"vmess","settings":{"vnext":[{"address":"jnda4.6bbt.tk","port":443,"users":[{"id":"6e41c22a-2794-4504-a05a-4f8def6d0bf5","alterId":0,"email":"t@t.tt","security":"auto"}]}]},"streamSettings":{"network":"ws","security":"","tlsSettings":{"allowInsecure":true,"serverName":"6bbt.tk"},"wsSettings":{"path":"/6bbt.tk","headers":{"Host":"6bbt.tk"}}},"tag":"proxy32"},{"mux":{"enabled":false,"concurrency":-1},"protocol":"trojan","settings":{"servers":[{"address":"146.19.215.81","method":"chacha20","ota":false,"password":"769c2da7-add3-42e8-a03c-07be9fcf483c","port":443,"level":1,"flow":""}]},"streamSettings":{"network":"tcp","security":"tls","tlsSettings":{"allowInsecure":true,"serverName":"zaelot.cc"},"wsSettings":{"path":"","headers":{"Host":""}}},"tag":"proxy33"},{"mux":{"enabled":false,"concurrency":-1},"protocol":"vmess","settings":{"vnext":[{"address":"fga3.6bbt.tk","port":443,"users":[{"id":"6e41c22a-2794-4504-a05a-4f8def6d0bf5","alterId":0,"email":"t@t.tt","security":"auto"}]}]},"streamSettings":{"network":"ws","security":"","tlsSettings":{"allowInsecure":true,"serverName":"6bbt.tk"},"wsSettings":{"path":"/6bbt.tk","headers":{"Host":"6bbt.tk"}}},"tag":"proxy34"},{"mux":{"enabled":false,"concurrency":-1},"protocol":"vmess","settings":{"vnext":[{"address":"fga4.6bbt.tk","port":443,"users":[{"id":"6e41c22a-2794-4504-a05a-4f8def6d0bf5","alterId":0,"email":"t@t.tt","security":"auto"}]}]},"streamSettings":{"network":"ws","security":"","tlsSettings":{"allowInsecure":true,"serverName":"6bbt.tk"},"wsSettings":{"path":"/6bbt.tk","headers":{"Host":"6bbt.tk"}}},"tag":"proxy35"},{"mux":{"enabled":false,"concurrency":-1},"protocol":"vmess","settings":{"vnext":[{"address":"172.67.147.152","port":443,"users":[{"id":"9e6ceeff-2546-3690-ac00-6fcdf31dec94","alterId":0,"email":"t@t.tt","security":"auto"}]}]},"streamSettings":{"network":"ws","security":"tls","tlsSettings":{"allowInsecure":true,"serverName":"v2fly.samrta.website"},"wsSettings":{"path":"/chcara","headers":{"Host":"v2fly.samrta.website"}}},"tag":"proxy36"},{"mux":{"enabled":false,"concurrency":-1},"protocol":"vmess","settings":{"vnext":[{"address":"144.34.175.46","port":80,"users":[{"id":"751192f4-437e-4ea9-f34f-4f0252509267","alterId":0,"email":"t@t.tt","security":"auto"}]}]},"streamSettings":{"network":"ws","security":"","tlsSettings":{"allowInsecure":true,"serverName":"144.34.175.46"},"wsSettings":{"path":"/","headers":{"Host":"144.34.175.46"}}},"tag":"proxy37"},{"mux":{"enabled":false,"concurrency":-1},"protocol":"vmess","settings":{"vnext":[{"address":"mastahgadungan.my.id","port":80,"users":[{"id":"f72faf3d-4da2-44ca-a23d-7813147612ff","alterId":0,"email":"t@t.tt","security":"auto"}]}]},"streamSettings":{"network":"ws","security":"","tlsSettings":{"allowInsecure":true,"serverName":"mastahgadungan.my.id"},"wsSettings":{"path":"/v2ray","headers":{"Host":"mastahgadungan.my.id"}}},"tag":"proxy38"},{"mux":{"enabled":false,"concurrency":-1},"protocol":"vmess","settings":{"vnext":[{"address":"zfc.windowsupdate1.com","port":443,"users":[{"id":"769c2da7-add3-42e8-a03c-07be9fcf483c","alterId":0,"email":"t@t.tt","security":"auto"}]}]},"streamSettings":{"network":"ws","security":"tls","tlsSettings":{"allowInsecure":true,"serverName":"nl.yfjc.sbs"},"wsSettings":{"path":"/yfjc/nl?ed=2048","headers":{"Host":"nl.yfjc.sbs"}}},"tag":"proxy39"},{"mux":{"enabled":false,"concurrency":-1},"protocol":"vmess","settings":{"vnext":[{"address":"zfc.windowsupdate1.com","port":443,"users":[{"id":"769c2da7-add3-42e8-a03c-07be9fcf483c","alterId":0,"email":"t@t.tt","security":"auto"}]}]},"streamSettings":{"network":"ws","security":"tls","tlsSettings":{"allowInsecure":true,"serverName":"us1.yfjc.sbs"},"wsSettings":{"path":"/yfjc/us1?ed=2048","headers":{"Host":"us1.yfjc.sbs"}}},"tag":"proxy40"},{"mux":{"enabled":false,"concurrency":-1},"protocol":"vmess","settings":{"vnext":[{"address":"zfc.windowsupdate1.com","port":443,"users":[{"id":"27509613-bbd5-403a-868c-8022d36aa565","alterId":0,"email":"t@t.tt","security":"auto"}]}]},"streamSettings":{"network":"ws","security":"tls","tlsSettings":{"allowInsecure":true,"serverName":"fr1.pqjc.buzz"},"wsSettings":{"path":"/pq/fr1?ed=2048","headers":{"Host":"fr1.pqjc.buzz"}}},"tag":"proxy41"},{"mux":{"enabled":false,"concurrency":-1},"protocol":"vmess","settings":{"vnext":[{"address":"cf-lt.sharecentre.online","port":443,"users":[{"id":"20e92881-5fb4-4b05-bc77-57929476dc69","alterId":0,"email":"t@t.tt","security":"auto"}]}]},"streamSettings":{"network":"ws","security":"tls","tlsSettings":{"allowInsecure":true,"serverName":"buyvm-ny.sharecentre.online"},"wsSettings":{"path":"/shirker","headers":{"Host":"buyvm-ny.sharecentre.online"}}},"tag":"proxy42"},{"mux":{"enabled":false,"concurrency":-1},"protocol":"vmess","settings":{"vnext":[{"address":"203.30.188.190","port":443,"users":[{"id":"17b2a313-37a0-4945-a8e4-e63375506b4a","alterId":0,"email":"t@t.tt","security":"auto"}]}]},"streamSettings":{"network":"ws","security":"tls","tlsSettings":{"allowInsecure":true,"serverName":"lg10.cfcdn1.xyz"},"wsSettings":{"path":"/A2DJOPFT","headers":{"Host":"lg10.cfcdn1.xyz"}}},"tag":"proxy43"},{"mux":{"enabled":false,"concurrency":-1},"protocol":"vmess","settings":{"vnext":[{"address":"jnda6.6bbt.tk","port":443,"users":[{"id":"6e41c22a-2794-4504-a05a-4f8def6d0bf5","alterId":0,"email":"t@t.tt","security":"auto"}]}]},"streamSettings":{"network":"ws","security":"","tlsSettings":{"allowInsecure":true,"serverName":"6bbt.tk"},"wsSettings":{"path":"/6bbt.tk","headers":{"Host":"6bbt.tk"}}},"tag":"proxy44"},{"mux":{"enabled":false,"concurrency":-1},"protocol":"vmess","settings":{"vnext":[{"address":"cf-lt.sharecentre.online","port":443,"users":[{"id":"20e92881-5fb4-4b05-bc77-57929476dc69","alterId":0,"email":"t@t.tt","security":"aes-128-gcm"}]}]},"streamSettings":{"network":"ws","security":"tls","tlsSettings":{"allowInsecure":true,"serverName":"kh.sharecentre.online"},"wsSettings":{"path":"/shirker","headers":{"Host":"kh.sharecentre.online"}}},"tag":"proxy45"},{"mux":{"enabled":false,"concurrency":-1},"protocol":"vmess","settings":{"vnext":[{"address":"141.193.213.21","port":443,"users":[{"id":"2b214122-1906-428a-bbb7-a039cbb7cd5c","alterId":0,"email":"t@t.tt","security":"auto"}]}]},"streamSettings":{"network":"ws","security":"tls","tlsSettings":{"allowInsecure":true,"serverName":"fr1.trump2023.org"},"wsSettings":{"path":"/9JZFDTKE","headers":{"Host":"fr1.trump2023.org"}}},"tag":"proxy46"},{"mux":{"enabled":false,"concurrency":-1},"protocol":"vmess","settings":{"vnext":[{"address":"zfc.windowsupdate1.com","port":443,"users":[{"id":"769c2da7-add3-42e8-a03c-07be9fcf483c","alterId":0,"email":"t@t.tt","security":"auto"}]}]},"streamSettings":{"network":"ws","security":"tls","tlsSettings":{"allowInsecure":true,"serverName":"us3.yfjc.sbs"},"wsSettings":{"path":"/yfjc/us3?ed=2048","headers":{"Host":"us3.yfjc.sbs"}}},"tag":"proxy47"},{"mux":{"enabled":false,"concurrency":-1},"protocol":"vmess","settings":{"vnext":[{"address":"fga2.6bbt.tk","port":443,"users":[{"id":"6e41c22a-2794-4504-a05a-4f8def6d0bf5","alterId":0,"email":"t@t.tt","security":"auto"}]}]},"streamSettings":{"network":"ws","security":"","tlsSettings":{"allowInsecure":true,"serverName":"6bbt.tk"},"wsSettings":{"path":"/6bbt.tk","headers":{"Host":"6bbt.tk"}}},"tag":"proxy48"},{"mux":{"enabled":false,"concurrency":-1},"protocol":"vmess","settings":{"vnext":[{"address":"23.227.38.38","port":443,"users":[{"id":"40d496a6-ceeb-4096-baeb-4cc52b205621","alterId":0,"email":"t@t.tt","security":"auto"}]}]},"streamSettings":{"network":"ws","security":"tls","tlsSettings":{"allowInsecure":true,"serverName":"lg1.trump2023.us"},"wsSettings":{"path":"/ECTCJ0DF","headers":{"Host":"lg1.trump2023.us"}}},"tag":"proxy49"},{"mux":{"enabled":false,"concurrency":-1},"protocol":"vless","settings":{"vnext":[{"address":"iiir.ddns.net","port":8443,"users":[{"id":"d11c0138-fb81-4a58-878e-0febe721c5c6","alterId":0,"email":"t@t.tt","security":"none","encryption":"none","flow":""}]}]},"streamSettings":{"network":"ws","security":"tls","tlsSettings":{"allowInsecure":true,"serverName":"wl.setam.fun"},"wsSettings":{"path":"/","headers":{"Host":"wl.setam.fun"}}},"tag":"proxy50"},{"mux":{"enabled":false,"concurrency":-1},"protocol":"vmess","settings":{"vnext":[{"address":"203.30.188.121","port":443,"users":[{"id":"c5a2d7b8-bf84-4f97-8577-b9b87f2baaf7","alterId":0,"email":"t@t.tt","security":"auto"}]}]},"streamSettings":{"network":"ws","security":"tls","tlsSettings":{"allowInsecure":true,"serverName":"oplg1.cfcdn2.xyz"},"wsSettings":{"path":"/AUIKN8AU","headers":{"Host":"oplg1.cfcdn2.xyz"}}},"tag":"proxy51"},{"mux":{"enabled":false,"concurrency":-1},"protocol":"vmess","settings":{"vnext":[{"address":"v9.gitvpn.eu.org","port":443,"users":[{"id":"d97c19fa-ca73-47c9-bf86-fe8fab547a36","alterId":0,"email":"t@t.tt","security":"auto"}]}]},"streamSettings":{"network":"grpc","security":"tls","tlsSettings":{"allowInsecure":true,"serverName":""},"wsSettings":{"path":"ihaxv9","headers":{"Host":""}}},"tag":"proxy52"},{"mux":{"enabled":false,"concurrency":-1},"protocol":"vmess","settings":{"vnext":[{"address":"nf2.6bbt.tk","port":443,"users":[{"id":"6e41c22a-2794-4504-a05a-4f8def6d0bf5","alterId":0,"email":"t@t.tt","security":"auto"}]}]},"streamSettings":{"network":"ws","security":"","tlsSettings":{"allowInsecure":true,"serverName":"6bbt.tk"},"wsSettings":{"path":"/6bbt.tk","headers":{"Host":"6bbt.tk"}}},"tag":"proxy53"},{"mux":{"enabled":false,"concurrency":-1},"protocol":"shadowsocks","settings":{"servers":[{"address":"172.99.188.99","method":"aes-256-gcm","ota":false,"password":"kDWvXYZoTBcGkC4","port":8882,"level":1,"flow":""}]},"streamSettings":{"network":"tcp","security":"","tlsSettings":{"allowInsecure":true,"serverName":""},"wsSettings":{"path":"","headers":{"Host":""}}},"tag":"proxy54"},{"mux":{"enabled":false,"concurrency":-1},"protocol":"vmess","settings":{"vnext":[{"address":"jnda3.6bbt.tk","port":443,"users":[{"id":"6e41c22a-2794-4504-a05a-4f8def6d0bf5","alterId":0,"email":"t@t.tt","security":"auto"}]}]},"streamSettings":{"network":"ws","security":"","tlsSettings":{"allowInsecure":true,"serverName":"6bbt.tk"},"wsSettings":{"path":"/6bbt.tk","headers":{"Host":"6bbt.tk"}}},"tag":"proxy55"},{"mux":{"enabled":false,"concurrency":-1},"protocol":"vmess","settings":{"vnext":[{"address":"vuk1.0bad.com","port":443,"users":[{"id":"927094d3-d678-4763-8591-e240d0bcae87","alterId":0,"email":"t@t.tt","security":"auto"}]}]},"streamSettings":{"network":"ws","security":"tls","tlsSettings":{"allowInsecure":true,"serverName":"vuk1.0bad.com"},"wsSettings":{"path":"/chat","headers":{"Host":"vuk1.0bad.com"}}},"tag":"proxy56"},{"mux":{"enabled":false,"concurrency":-1},"protocol":"vless","settings":{"vnext":[{"address":"iiir.ddns.net","port":2087,"users":[{"id":"3cbda2ba-64bb-46b4-bb7e-d84e7a19af0c","alterId":0,"email":"t@t.tt","security":"none","encryption":"none","flow":""}]}]},"streamSettings":{"network":"ws","security":"tls","tlsSettings":{"allowInsecure":true,"serverName":"gate.setam.fun"},"wsSettings":{"path":"/","headers":{"Host":"gate.setam.fun"}}},"tag":"proxy57"},{"mux":{"enabled":false,"concurrency":-1},"protocol":"vmess","settings":{"vnext":[{"address":"ingress-i2.iivvppnn.info","port":38102,"users":[{"id":"79386685-16da-327c-9e14-aa6d702d86bc","alterId":1,"email":"t@t.tt","security":"auto"}]}]},"streamSettings":{"network":"ws","security":"","tlsSettings":{"allowInsecure":true,"serverName":"YTB-AWKJ"},"wsSettings":{"path":"/hls/cctv5phd.m3u8","headers":{"Host":"YTB-AWKJ"}}},"tag":"proxy58"},{"mux":{"enabled":false,"concurrency":-1},"protocol":"vless","settings":{"vnext":[{"address":"iiir.ddns.net","port":8443,"users":[{"id":"6912aa57-adad-4217-baac-a79391e1e88d","alterId":0,"email":"t@t.tt","security":"none","encryption":"none","flow":""}]}]},"streamSettings":{"network":"ws","security":"tls","tlsSettings":{"allowInsecure":true,"serverName":"wl.setam.fun"},"wsSettings":{"path":"/","headers":{"Host":"wl.setam.fun"}}},"tag":"proxy59"},{"mux":{"enabled":false,"concurrency":-1},"protocol":"vmess","settings":{"vnext":[{"address":"103.21.244.173","port":80,"users":[{"id":"f7738290-ba04-4dd1-b4f3-e6863a9e1c8a","alterId":0,"email":"t@t.tt","security":"auto"}]}]},"streamSettings":{"network":"ws","security":"","tlsSettings":{"allowInsecure":true,"serverName":"zzsg.nmsl.pics"},"wsSettings":{"path":"/","headers":{"Host":"zzsg.nmsl.pics"}}},"tag":"proxy60"},{"mux":{"enabled":false,"concurrency":-1},"protocol":"vmess","settings":{"vnext":[{"address":"ingress-i2.iivvppnn.info","port":38102,"users":[{"id":"79386685-16da-327c-9e14-aa6d702d86bc","alterId":1,"email":"t@t.tt","security":"auto"}]}]},"streamSettings":{"network":"ws","security":"","tlsSettings":{"allowInsecure":true,"serverName":"YTB-awkj"},"wsSettings":{"path":"/hls/cctv5phd.m3u8","headers":{"Host":"YTB-awkj"}}},"tag":"proxy61"},{"mux":{"enabled":false,"concurrency":-1},"protocol":"vmess","settings":{"vnext":[{"address":"cf-lt-dns.sharecentre.online","port":443,"users":[{"id":"20e92881-5fb4-4b05-bc77-57929476dc69","alterId":0,"email":"t@t.tt","security":"auto"}]}]},"streamSettings":{"network":"ws","security":"tls","tlsSettings":{"allowInsecure":true,"serverName":"kh.sharecentre.online"},"wsSettings":{"path":"/shirker","headers":{"Host":"kh.sharecentre.online"}}},"tag":"proxy62"},{"mux":{"enabled":false,"concurrency":-1},"protocol":"vmess","settings":{"vnext":[{"address":"203.30.191.9","port":443,"users":[{"id":"c5a2d7b8-bf84-4f97-8577-b9b87f2baaf7","alterId":0,"email":"t@t.tt","security":"auto"}]}]},"streamSettings":{"network":"ws","security":"tls","tlsSettings":{"allowInsecure":true,"serverName":"oplg1.cfcdn2.xyz"},"wsSettings":{"path":"/AUIKN8AU","headers":{"Host":"oplg1.cfcdn2.xyz"}}},"tag":"proxy63"},{"mux":{"enabled":false,"concurrency":-1},"protocol":"vmess","settings":{"vnext":[{"address":"buyvm.sharecentre.online","port":443,"users":[{"id":"20e92881-5fb4-4b05-bc77-57929476dc69","alterId":0,"email":"t@t.tt","security":"auto"}]}]},"streamSettings":{"network":"ws","security":"tls","tlsSettings":{"allowInsecure":true,"serverName":"buyvm.sharecentre.online"},"wsSettings":{"path":"/shirker","headers":{"Host":"buyvm.sharecentre.online"}}},"tag":"proxy64"},{"mux":{"enabled":false,"concurrency":-1},"protocol":"vmess","settings":{"vnext":[{"address":"vsg1.0bad.com","port":443,"users":[{"id":"927094d3-d678-4763-8591-e240d0bcae87","alterId":0,"email":"t@t.tt","security":"auto"}]}]},"streamSettings":{"network":"ws","security":"tls","tlsSettings":{"allowInsecure":true,"serverName":"vsg1.0bad.com"},"wsSettings":{"path":"/chat","headers":{"Host":"vsg1.0bad.com"}}},"tag":"proxy65"},{"mux":{"enabled":false,"concurrency":-1},"protocol":"vmess","settings":{"vnext":[{"address":"news.microsoft.com","port":443,"users":[{"id":"2b214122-1906-428a-bbb7-a039cbb7cd5c","alterId":0,"email":"t@t.tt","security":"auto"}]}]},"streamSettings":{"network":"ws","security":"tls","tlsSettings":{"allowInsecure":true,"serverName":"fr1.trump2023.org"},"wsSettings":{"path":"/9JZFDTKE","headers":{"Host":"fr1.trump2023.org"}}},"tag":"proxy66"},{"mux":{"enabled":false,"concurrency":-1},"protocol":"vmess","settings":{"vnext":[{"address":"haxus3.janechiu.icu","port":443,"users":[{"id":"0df258cb-a376-4b8e-a378-a556a4658aeb","alterId":0,"email":"t@t.tt","security":"auto"}]}]},"streamSettings":{"network":"ws","security":"tls","tlsSettings":{"allowInsecure":true,"serverName":"haxus3.janechiu.icu"},"wsSettings":{"path":"/","headers":{"Host":"haxus3.janechiu.icu"}}},"tag":"proxy67"},{"mux":{"enabled":false,"concurrency":-1},"protocol":"vmess","settings":{"vnext":[{"address":"103.21.244.195","port":443,"users":[{"id":"40d496a6-ceeb-4096-baeb-4cc52b205621","alterId":0,"email":"t@t.tt","security":"auto"}]}]},"streamSettings":{"network":"ws","security":"tls","tlsSettings":{"allowInsecure":true,"serverName":"lg1.trump2023.us"},"wsSettings":{"path":"/ECTCJ0DF","headers":{"Host":"lg1.trump2023.us"}}},"tag":"proxy68"},{"mux":{"enabled":false,"concurrency":-1},"protocol":"vmess","settings":{"vnext":[{"address":"172.67.199.115","port":443,"users":[{"id":"20e92881-5fb4-4b05-bc77-57929476dc69","alterId":0,"email":"t@t.tt","security":"auto"}]}]},"streamSettings":{"network":"ws","security":"tls","tlsSettings":{"allowInsecure":true,"serverName":"lu.sharecentre.online"},"wsSettings":{"path":"/shirker","headers":{"Host":"lu.sharecentre.online"}}},"tag":"proxy69"},{"mux":{"enabled":false,"concurrency":-1},"protocol":"vless","settings":{"vnext":[{"address":"172.67.166.169","port":443,"users":[{"id":"146edc71-e452-4553-ec30-8c7a5b5c8d9b","alterId":0,"email":"t@t.tt","security":"none","encryption":"none","flow":""}]}]},"streamSettings":{"network":"ws","security":"tls","tlsSettings":{"allowInsecure":true,"serverName":"abc.vpneee.top"},"wsSettings":{"path":"/vpneee","headers":{"Host":"abc.vpneee.top"}}},"tag":"proxy70"},{"protocol":"freedom","settings":{},"tag":"direct"},{"protocol":"blackhole","settings":{"response":{"type":"http"}},"tag":"block"}],"policy":{"system":{"statsOutboundDownlink":true,"statsOutboundUplink":true}},"routing":{"balancers":[{"selector":["proxy0","proxy1","proxy2","proxy3","proxy4","proxy5","proxy6","proxy7","proxy8","proxy9","proxy10","proxy11","proxy12","proxy13","proxy14","proxy15","proxy16","proxy17","proxy18","proxy19","proxy20","proxy21","proxy22","proxy23","proxy24","proxy25","proxy26","proxy27","proxy28","proxy29","proxy30","proxy31","proxy32","proxy33","proxy34","proxy35","proxy36","proxy37","proxy38","proxy39","proxy40","proxy41","proxy42","proxy43","proxy44","proxy45","proxy46","proxy47","proxy48","proxy49","proxy50","proxy51","proxy52","proxy53","proxy54","proxy55","proxy56","proxy57","proxy58","proxy59","proxy60","proxy61","proxy62","proxy63","proxy64","proxy65","proxy66","proxy67","proxy68","proxy69","proxy70"],"strategy":{"type":"random"},"tag":"balancer"}],"domainStrategy":"IPIfNonMatch","rules":[{"enabled":true,"inboundTag":["api"],"outboundTag":"api","type":"field"},{"domain":["domain:example-example.com","domain:example-example2.com"],"enabled":true,"outboundTag":"direct","type":"field"},{"domain":["geosite:category-ads-all"],"enabled":true,"outboundTag":"block","type":"field"},{"domain":["geosite:cn"],"enabled":true,"outboundTag":"direct","type":"field"},{"enabled":true,"ip":["geoip:private","geoip:cn"],"outboundTag":"direct","type":"field"},{"balancerTag":"balancer","network":"tcp,udp","type":"field"}]},"stats":{}}